LICENSE.txt
MANIFEST.in
README.rst
requirements.txt
rtd.txt
setup.cfg
setup.py
kotti_site_settings/__init__.py
kotti_site_settings/fanstatic.py
kotti_site_settings/resources.py
kotti_site_settings/util.py
kotti_site_settings.egg-info/PKG-INFO
kotti_site_settings.egg-info/SOURCES.txt
kotti_site_settings.egg-info/dependency_links.txt
kotti_site_settings.egg-info/entry_points.txt
kotti_site_settings.egg-info/not-zip-safe
kotti_site_settings.egg-info/requires.txt
kotti_site_settings.egg-info/top_level.txt
kotti_site_settings/alembic/README
kotti_site_settings/alembic/env.py
kotti_site_settings/alembic/script.py.mako
kotti_site_settings/alembic/versions/.gitkeep
kotti_site_settings/alembic/versions/README.md
kotti_site_settings/locale/.gitkeep
kotti_site_settings/locale/README
kotti_site_settings/static/scripts.js
kotti_site_settings/static/scripts.min.js
kotti_site_settings/static/styles.css
kotti_site_settings/static/styles.min.css
kotti_site_settings/templates/add_option.pt
kotti_site_settings/templates/options.pt
kotti_site_settings/templates/settings.pt
kotti_site_settings/templates/view.pt
kotti_site_settings/tests/conftest.py
kotti_site_settings/tests/test_functional.py
kotti_site_settings/tests/test_resources.py
kotti_site_settings/tests/test_view.py
kotti_site_settings/views/__init__.py
kotti_site_settings/views/edit.py
kotti_site_settings/views/view.py